anonymizer_lib/__init__.py
anonymizer_lib/anonymizer.py
anonymizer_lib/config_generator.py
anonymizer_lib-0.1.3.dist-info/METADATA
anonymizer_lib-0.1.3.dist-info/WHEEL
anonymizer_lib-0.1.3.dist-info/top_level.txt
anonymizer_lib-0.1.3.dist-info/RECORD
