Metadata-Version: 2.4
Name: anonymizer_lib
Version: 0.1.3
Summary: A simple library for anonymizing sensitive words
Home-page: https://github.com/kvigneshwar96-droid/anonymizer_lib.git
Author: Vigneshwar K
Author-email: k.vigneshwar96@gmail.com
Requires-Python: >=3.7
Dynamic: author
Dynamic: author-email
Dynamic: description
Dynamic: description-content-type
Dynamic: home-page
Dynamic: requires-python
Dynamic: summary
